[
  {
    "name": "Carrot",
    "cost": 5,
    "growth_time": 3000,
    "harvest_price": 10,
    "harvest_amount": 10,
    "tile_image": "carrot.png",
    "nitrogen_use": 2,
    "phosphorus_use": 3,
    "potassium_use": 2,
    "calcium_use": 1,
    "magnesium_use": 1,
    "sulfur_use": 1,
    "water_use": 2,
    "nitrogen_double": 10,
    "phosphorus_double": 10,
    "potassium_double": 10,
    "calcium_double": 10,
    "magnesium_double": 10,
    "sulfur_double": 10,
    "water_double": 10
  },
  {
    "name": "Tomato",
    "cost": 8,
    "growth_time": 4000,
    "harvest_price": 15,
    "harvest_amount": 10,
    "tile_image": "tomato.png",
    "nitrogen_use": 3,
    "phosphorus_use": 3,
    "potassium_use": 4,
    "calcium_use": 3,
    "magnesium_use": 2,
    "sulfur_use": 2,
    "water_use": 3,
    "nitrogen_double": 15,
    "phosphorus_double": 15,
    "potassium_double": 15,
    "calcium_double": 15,
    "magnesium_double": 15,
    "sulfur_double": 15,
    "water_double": 15
  },
  {
    "name": "Blueberry",
    "cost": 50,
    "growth_time": 30000,
    "harvest_price": 100,
    "harvest_amount": 10,
    "tile_image": "blueberry.png",
    "nitrogen_use": 2,
    "phosphorus_use": 2,
    "potassium_use": 2,
    "calcium_use": 1,
    "magnesium_use": 1,
    "sulfur_use": 1,
    "water_use": 2,
    "nitrogen_double": 100,
    "phosphorus_double": 100,
    "potassium_double": 100,
    "calcium_double": 100,
    "magnesium_double": 100,
    "sulfur_double": 100,
    "water_double": 100
  },
  {
    "name": "Corn",
    "cost": 9,
    "growth_time": 5000,
    "harvest_price": 18,
    "harvest_amount": 10,
    "tile_image": "corn.png",
    "nitrogen_use": 5,
    "phosphorus_use": 3,
    "potassium_use": 3,
    "calcium_use": 2,
    "magnesium_use": 2,
    "sulfur_use": 2,
    "water_use": 3,
    "nitrogen_double": 18,
    "phosphorus_double": 18,
    "potassium_double": 18,
    "calcium_double": 18,
    "magnesium_double": 18,
    "sulfur_double": 18,
    "water_double": 18
  },
  {
    "name": "Wheat",
    "cost": 6,
    "growth_time": 3200,
    "harvest_price": 11,
    "harvest_amount": 10,
    "tile_image": "wheat.png",
    "nitrogen_use": 2,
    "phosphorus_use": 2,
    "potassium_use": 1,
    "calcium_use": 1,
    "magnesium_use": 1,
    "sulfur_use": 1,
    "water_use": 2,
    "nitrogen_double": 11,
    "phosphorus_double": 11,
    "potassium_double": 11,
    "calcium_double": 11,
    "magnesium_double": 11,
    "sulfur_double": 11,
    "water_double": 11
  },
  {
    "name": "Rice",
    "cost": 10,
    "growth_time": 4200,
    "harvest_price": 16,
    "harvest_amount": 10,
    "tile_image": "rice.png",
    "nitrogen_use": 2,
    "phosphorus_use": 2,
    "potassium_use": 3,
    "calcium_use": 1,
    "magnesium_use": 2,
    "sulfur_use": 1,
    "water_use": 5,
    "nitrogen_double": 16,
    "phosphorus_double": 16,
    "potassium_double": 16,
    "calcium_double": 16,
    "magnesium_double": 16,
    "sulfur_double": 16,
    "water_double": 16
  },
  {
    "name": "Soybeans",
    "cost": 10,
    "growth_time": 5000,
    "harvest_price": 18,
    "harvest_amount": 10,
    "tile_image": "soybeans.png",
    "nitrogen_use": 3,
    "phosphorus_use": 3,
    "potassium_use": 3,
    "calcium_use": 2,
    "magnesium_use": 2,
    "sulfur_use": 2,
    "water_use": 2,
    "nitrogen_double": 18,
    "phosphorus_double": 18,
    "potassium_double": 18,
    "calcium_double": 18,
    "magnesium_double": 18,
    "sulfur_double": 18,
    "water_double": 18
  },
  {
    "name": "Sugar Cane",
    "cost": 15,
    "growth_time": 12000,
    "harvest_price": 35,
    "harvest_amount": 10,
    "tile_image": "sugar_cane.png",
    "nitrogen_use": 3,
    "phosphorus_use": 2,
    "potassium_use": 4,
    "calcium_use": 2,
    "magnesium_use": 2,
    "sulfur_use": 2,
    "water_use": 4,
    "nitrogen_double": 35,
    "phosphorus_double": 35,
    "potassium_double": 35,
    "calcium_double": 35,
    "magnesium_double": 35,
    "sulfur_double": 35,
    "water_double": 35
  },
  {
    "name": "Potatoes",
    "cost": 7,
    "growth_time": 3700,
    "harvest_price": 14,
    "harvest_amount": 10,
    "tile_image": "potatoes.png",
    "nitrogen_use": 3,
    "phosphorus_use": 3,
    "potassium_use": 5,
    "calcium_use": 2,
    "magnesium_use": 1,
    "sulfur_use": 1,
    "water_use": 2,
    "nitrogen_double": 14,
    "phosphorus_double": 14,
    "potassium_double": 14,
    "calcium_double": 14,
    "magnesium_double": 14,
    "sulfur_double": 14,
    "water_double": 14
  },
  {
    "name": "Onions",
    "cost": 6,
    "growth_time": 3100,
    "harvest_price": 10,
    "harvest_amount": 10,
    "tile_image": "onions.png",
    "nitrogen_use": 2,
    "phosphorus_use": 2,
    "potassium_use": 2,
    "calcium_use": 1,
    "magnesium_use": 1,
    "sulfur_use": 3,
    "water_use": 2,
    "nitrogen_double": 10,
    "phosphorus_double": 10,
    "potassium_double": 10,
    "calcium_double": 10,
    "magnesium_double": 10,
    "sulfur_double": 10,
    "water_double": 10
  },
  {
    "name": "Lettuce",
    "cost": 3,
    "growth_time": 1500,
    "harvest_price": 6,
    "harvest_amount": 10,
    "tile_image": "lettuce.png",
    "nitrogen_use": 3,
    "phosphorus_use": 1,
    "potassium_use": 2,
    "calcium_use": 1,
    "magnesium_use": 1,
    "sulfur_use": 1,
    "water_use": 2,
    "nitrogen_double": 6,
    "phosphorus_double": 6,
    "potassium_double": 6,
    "calcium_double": 6,
    "magnesium_double": 6,
    "sulfur_double": 6,
    "water_double": 6
  },
  {
    "name": "Strawberry",
    "cost": 12,
    "growth_time": 4500,
    "harvest_price": 22,
    "harvest_amount": 10,
    "tile_image": "strawberry.png",
    "nitrogen_use": 2,
    "phosphorus_use": 3,
    "potassium_use": 3,
    "calcium_use": 1,
    "magnesium_use": 1,
    "sulfur_use": 1,
    "water_use": 2,
    "nitrogen_double": 22,
    "phosphorus_double": 22,
    "potassium_double": 22,
    "calcium_double": 22,
    "magnesium_double": 22,
    "sulfur_double": 22,
    "water_double": 22
  },
  {
    "name": "Bell Pepper",
    "cost": 9,
    "growth_time": 4200,
    "harvest_price": 17,
    "harvest_amount": 10,
    "tile_image": "bell_pepper.png",
    "nitrogen_use": 3,
    "phosphorus_use": 3,
    "potassium_use": 3,
    "calcium_use": 2,
    "magnesium_use": 2,
    "sulfur_use": 2,
    "water_use": 3,
    "nitrogen_double": 17,
    "phosphorus_double": 17,
    "potassium_double": 17,
    "calcium_double": 17,
    "magnesium_double": 17,
    "sulfur_double": 17,
    "water_double": 17
  },
  {
    "name": "Broccoli",
    "cost": 11,
    "growth_time": 5500,
    "harvest_price": 20,
    "harvest_amount": 10,
    "tile_image": "broccoli.png",
    "nitrogen_use": 4,
    "phosphorus_use": 2,
    "potassium_use": 3,
    "calcium_use": 3,
    "magnesium_use": 2,
    "sulfur_use": 3,
    "water_use": 3,
    "nitrogen_double": 20,
    "phosphorus_double": 20,
    "potassium_double": 20,
    "calcium_double": 20,
    "magnesium_double": 20,
    "sulfur_double": 20,
    "water_double": 20
  },
  {
    "name": "Pumpkin",
    "cost": 18,
    "growth_time": 6000,
    "harvest_price": 40,
    "harvest_amount": 10,
    "tile_image": "pumpkin.png",
    "nitrogen_use": 3,
    "phosphorus_use": 4,
    "potassium_use": 4,
    "calcium_use": 2,
    "magnesium_use": 2,
    "sulfur_use": 1,
    "water_use": 4,
    "nitrogen_double": 40,
    "phosphorus_double": 40,
    "potassium_double": 40,
    "calcium_double": 40,
    "magnesium_double": 40,
    "sulfur_double": 40,
    "water_double": 40
  },
  {
    "name": "Watermelon",
    "cost": 20,
    "growth_time": 6500,
    "harvest_price": 45,
    "harvest_amount": 10,
    "tile_image": "watermelon.png",
    "nitrogen_use": 3,
    "phosphorus_use": 3,
    "potassium_use": 4,
    "calcium_use": 2,
    "magnesium_use": 2,
    "sulfur_use": 1,
    "water_use": 5,
    "nitrogen_double": 45,
    "phosphorus_double": 45,
    "potassium_double": 45,
    "calcium_double": 45,
    "magnesium_double": 45,
    "sulfur_double": 45,
    "water_double": 45
  },
  {
    "name": "Grapes",
    "cost": 60,
    "growth_time": 35000,
    "harvest_price": 120,
    "harvest_amount": 10,
    "tile_image": "grapes.png",
    "nitrogen_use": 2,
    "phosphorus_use": 2,
    "potassium_use": 3,
    "calcium_use": 2,
    "magnesium_use": 1,
    "sulfur_use": 1,
    "water_use": 2,
    "nitrogen_double": 120,
    "phosphorus_double": 120,
    "potassium_double": 120,
    "calcium_double": 120,
    "magnesium_double": 120,
    "sulfur_double": 120,
    "water_double": 120
  },
  {
    "name": "Sunflower",
    "cost": 8,
    "growth_time": 5200,
    "harvest_price": 16,
    "harvest_amount": 10,
    "tile_image": "sunflower.png",
    "nitrogen_use": 3,
    "phosphorus_use": 2,
    "potassium_use": 2,
    "calcium_use": 2,
    "magnesium_use": 2,
    "sulfur_use": 1,
    "water_use": 1,
    "nitrogen_double": 16,
    "phosphorus_double": 16,
    "potassium_double": 16,
    "calcium_double": 16,
    "magnesium_double": 16,
    "sulfur_double": 16,
    "water_double": 16
  },
  {
    "name": "Cotton",
    "cost": 25,
    "growth_time": 8000,
    "harvest_price": 55,
    "harvest_amount": 10,
    "tile_image": "cotton.png",
    "nitrogen_use": 4,
    "phosphorus_use": 3,
    "potassium_use": 4,
    "calcium_use": 3,
    "magnesium_use": 2,
    "sulfur_use": 2,
    "water_use": 3,
    "nitrogen_double": 55,
    "phosphorus_double": 55,
    "potassium_double": 55,
    "calcium_double": 55,
    "magnesium_double": 55,
    "sulfur_double": 55,
    "water_double": 55
  },
  {
    "name": "Coffee Bean",
    "cost": 80,
    "growth_time": 40000,
    "harvest_price": 150,
    "harvest_amount": 10,
    "tile_image": "coffee_bean.png",
    "nitrogen_use": 4,
    "phosphorus_use": 2,
    "potassium_use": 4,
    "calcium_use": 1,
    "magnesium_use": 2,
    "sulfur_use": 2,
    "water_use": 3,
    "nitrogen_double": 150,
    "phosphorus_double": 150,
    "potassium_double": 150,
    "calcium_double": 150,
    "magnesium_double": 150,
    "sulfur_double": 150,
    "water_double": 150
  }
]